CryptoConf/__init__.py
CryptoConf/main.py
CryptoConf-0.0.4.dist-info/LICENSE.txt
CryptoConf-0.0.4.dist-info/METADATA
CryptoConf-0.0.4.dist-info/WHEEL
CryptoConf-0.0.4.dist-info/top_level.txt
CryptoConf-0.0.4.dist-info/RECORD
