Metadata-Version: 2.1
Name: CryptoConf
Version: 0.0.4
Author: Leora
Author-email: Leora@gmail.com
License: MIT
Classifier: Programming Language :: Python :: 3
Classifier: License :: OSI Approved :: MIT License
Classifier: Operating System :: OS Independent
License-File: LICENSE.txt
